voxface/__init__.py
voxface/__main__.py
voxface/templates/ConteCore2_50_2mm_deface_mask.nii.gz
voxface/templates/ConteCore2_50_T1w_2mm.nii.gz
voxface-2024.7.23.dist-info/LICENSE
voxface-2024.7.23.dist-info/METADATA
voxface-2024.7.23.dist-info/WHEEL
voxface-2024.7.23.dist-info/entry_points.txt
voxface-2024.7.23.dist-info/top_level.txt
voxface-2024.7.23.dist-info/RECORD
