Metadata-Version: 2.1
Name: voxface
Version: 2024.7.23
Summary: Fast MRI face voxelator
Home-page: https://github.com/jmtyszka/voxface
Author: Julian Michael Tyszka
Author-email: jmt@caltech.edu
Project-URL: Bug Reports, https://github.com/jmtyszka/voxface/issues
Project-URL: Funding, http://conte.caltech.edu/
Project-URL: Source, https://github.com/jmtyszka/voxface/
Keywords: neuroimaging MRI Nifti deface deidentify
Classifier: Development Status :: 3 - Alpha
Classifier: Intended Audience :: Science/Research
Classifier: Topic :: Scientific/Engineering :: Image Processing
Classifier: License :: OSI Approved :: MIT License
Classifier: Programming Language :: Python :: 3.8
Classifier: Programming Language :: Python :: 3.9
Requires-Python: >=3.8, <4
License-File: LICENSE
